{
	"Tolerant": {
	  "Duplicated Value Smell": {
		"mostly": 0.9
	  },
	  "Extreme Value Smell": {
		"mostly": 0.9,
		"threshold": 3
	  },
	  "Suspect Sign Smell": {
		"mostly": 0.9,
		"percentile_threshold": 0
	  },
	  "Casing Smell": {
		"mostly": 0.9,
		"same_case_wordcount_threshold": 0
	  },
	  "Long Data Value Smell": {
		"mostly": 0.9,
		"length_threshold": 0
	  },
	  "Missing Value Smell": {
		"mostly": 0.9
	  },
	  "Floating Point Number As String Smell": {
		"mostly": 0.01
	  },
	  "Integer As Floating Point Number Smell": {
		"mostly": 0.01,
		"epsilon": 0
	  },
	  "Integer As String Smell": {
		"mostly": 0.01
	  }
	},
	"Medium": {
	  "Duplicated Value Smell": {
		"mostly": 0.95
	  },
	  "Extreme Value Smell": {
		"mostly": 0.95,
		"threshold": 3
	  },
	  "Suspect Sign Smell": {
		"mostly": 0.95
	  },
	  "Casing Smell": {
		"mostly": 0.95
	  },
	  "Long Data Value Smell": {
		"mostly": 0.95
	  },
	  "Missing Value Smell": {
		"mostly": 0.95
	  },
	  "Floating Point Number As String Smell": {
		"mostly": 0.1
	  },
	  "Integer As Floating Point Number Smell": {
		"mostly": 0.1
	  },
	  "Integer As String Smell": {
		"mostly": 0.1
	  }
	},
	"Strict": {
	  "Duplicated Value Smell": {
		"mostly": 1
	  },
	  "Extreme Value Smell": {
		"mostly": 1,
		"threshold": 3
	  },
	  "Suspect Sign Smell": {
		"mostly": 1
	  },
	  "Casing Smell": {
		"mostly": 1
	  },
	  "Long Data Value Smell": {
		"mostly": 1
	  },
	  "Missing Value Smell": {
		"mostly": 1
	  },
	  "Floating Point Number As String Smell": {
		"mostly": 0.2
	  },
	  "Integer As Floating Point Number Smell": {
		"mostly": 0.2
	  },
	  "Integer As String Smell": {
		"mostly": 0.2
	  }
	}
  }